odoo/addons/product_secondary_unit/README.rst
odoo/addons/product_secondary_unit/__init__.py
odoo/addons/product_secondary_unit/__manifest__.py
odoo/addons/product_secondary_unit/i18n/es.po
odoo/addons/product_secondary_unit/i18n/es_MX.po
odoo/addons/product_secondary_unit/i18n/fr.po
odoo/addons/product_secondary_unit/i18n/hr.po
odoo/addons/product_secondary_unit/i18n/it.po
odoo/addons/product_secondary_unit/i18n/ja.po
odoo/addons/product_secondary_unit/i18n/ja_JP.po
odoo/addons/product_secondary_unit/i18n/product_secondary_unit.pot
odoo/addons/product_secondary_unit/i18n/pt_BR.po
odoo/addons/product_secondary_unit/i18n/tr.po
odoo/addons/product_secondary_unit/i18n/zh_CN.po
odoo/addons/product_secondary_unit/models/__init__.py
odoo/addons/product_secondary_unit/models/product_product.py
odoo/addons/product_secondary_unit/models/product_second_unit.py
odoo/addons/product_secondary_unit/models/product_secondary_unit_mixin.py
odoo/addons/product_secondary_unit/models/product_template.py
odoo/addons/product_secondary_unit/readme/CONTRIBUTORS.md
odoo/addons/product_secondary_unit/readme/DESCRIPTION.md
odoo/addons/product_secondary_unit/readme/USAGE.md
odoo/addons/product_secondary_unit/security/ir.model.access.csv
odoo/addons/product_secondary_unit/static/description/icon.png
odoo/addons/product_secondary_unit/static/description/index.html
odoo/addons/product_secondary_unit/tests/__init__.py
odoo/addons/product_secondary_unit/tests/models.py
odoo/addons/product_secondary_unit/tests/test_product_second_unit.py
odoo/addons/product_secondary_unit/tests/test_secondary_unit_mixin.py
odoo/addons/product_secondary_unit/views/product_views.xml
odoo_addon_product_secondary_unit-18.0.1.1.0.3.dist-info/METADATA
odoo_addon_product_secondary_unit-18.0.1.1.0.3.dist-info/WHEEL
odoo_addon_product_secondary_unit-18.0.1.1.0.3.dist-info/top_level.txt
odoo_addon_product_secondary_unit-18.0.1.1.0.3.dist-info/RECORD
